jaxkd/__init__.py
jaxkd/cukd.py
jaxkd/extras.py
jaxkd/tree.py
jaxkd-0.1.2.dist-info/METADATA
jaxkd-0.1.2.dist-info/WHEEL
jaxkd-0.1.2.dist-info/licenses/LICENSE
jaxkd-0.1.2.dist-info/RECORD
