Metadata-Version: 2.4
Name: jaxkd
Version: 0.1.2
Summary: Minimal JAX implementation of k-nearest neighbors using a k-d tree.
Project-URL: Source, https://github.com/dodgebc/jaxkd
Author-email: Benjamin Dodge <bendodge@stanford.edu>
License-Expression: MIT
License-File: LICENSE
Requires-Python: >=3.10
Requires-Dist: jax
Provides-Extra: cuda
Requires-Dist: jax[cuda12]; extra == 'cuda'
Requires-Dist: jaxkd-cuda; extra == 'cuda'
Provides-Extra: dev
Requires-Dist: ipywidgets>=8.1.7; extra == 'dev'
Requires-Dist: jax[cuda12]==0.6.0; extra == 'dev'
Requires-Dist: jupyterlab>=4.4.3; extra == 'dev'
Requires-Dist: matplotlib>=3.10.3; extra == 'dev'
Requires-Dist: pytest>=8.3.5; extra == 'dev'
Requires-Dist: ruff>=0.11.11; extra == 'dev'
Requires-Dist: tqdm>=4.67.1; extra == 'dev'
